{
    "roles": [
      {
          "name": "ss2owner",
          "description": "SS2 owner"
      }
    ],
    "scopes": [
      {
        "id": "supplierpanel",
        "description": "supplier panel"
      }      
    ],
    "role_scopes": [
      {
        "role_name": "ss2owner",
        "scope_id": "supplierpanel"
      }
    ],
    "permissions": [
      {
          "id": "supplierpanel:supplierlistapi:view",
          "description": "supplier list api view",
          "scope_id": "supplierpanel"
      },
      {
          "id": "supplierpanel:supplierlistadminapi:admin",
          "description": "supplier api admin",
          "scope_id": "supplierpanel"
      }
    ],
    "role_permissions": [
      {
        "role_name": "ss2owner",
        "permission_id": "supplierpanel:supplierlistapi:view"
      },
      {
        "role_name": "ss2owner",
        "permission_id": "supplierpanel:supplierlistadminapi:admin"
      }
    ],
    "route_permissions": [
        {
            "route": "/supplier/list",
            "request_method": "GET",
            "service": "ss2",
            "required_permission_id": "supplierpanel:supplierlistapi:view"
        },
        {
          "route": "/supplier/list_with_address",
          "request_method": "GET",
          "service": "ss2",
          "required_permission_id": "supplierpanel:supplierlistapi:view"
        },
        {
          "route": "/supplier/add",
          "request_method": "POST",
          "service": "ss2",
          "required_permission_id": "supplierpanel:supplierlistadminapi:admin"
        },
        {
          "route": "/supplier/edit",
          "request_method": "POST",
          "service": "ss2",
          "required_permission_id": "supplierpanel:supplierlistadminapi:admin"
        },
        {
          "route": "/supplier_address/list",
          "request_method": "GET",
          "service": "ss2",
          "required_permission_id": "supplierpanel:supplierlistapi:view"
        },
        {
          "route": "/supplier_address/add",
          "request_method": "POST",
          "service": "ss2",
          "required_permission_id": "supplierpanel:supplierlistadminapi:admin"
        },
        {
          "route": "/supplier_address/edit",
          "request_method": "POST",
          "service": "ss2",
          "required_permission_id": "supplierpanel:supplierlistadminapi:admin"
        },
        {
          "route": "/payment_account_detail/list",
          "request_method": "GET",
          "service": "ss2",
          "required_permission_id": "supplierpanel:supplierlistapi:view"
        },
        {
          "route": "/payment_account_detail/add",
          "request_method": "POST",
          "service": "ss2",
          "required_permission_id": "supplierpanel:supplierlistadminapi:admin"
        },
        {
          "route": "/payment_account_detail/edit",
          "request_method": "POST",
          "service": "ss2",
          "required_permission_id": "supplierpanel:supplierlistadminapi:admin"
        },
        {
          "route": "/key_account_manager/list",
          "request_method": "GET",
          "service": "ss2",
          "required_permission_id": "supplierpanel:supplierlistapi:view"
        },
        {
          "route": "/key_account_manager/add",
          "request_method": "POST",
          "service": "ss2",
          "required_permission_id": "supplierpanel:supplierlistadminapi:admin"
        },
        {
          "route": "/bank/list",
          "request_method": "GET",
          "service": "ss2",
          "required_permission_id": "supplierpanel:supplierlistapi:view"
        },
        {
          "route": "/key_account_manager/edit",
          "request_method": "POST",
          "service": "ss2",
          "required_permission_id": "supplierpanel:supplierlistadminapi:admin"
        }
    ]
}